[{"_id":{"$oid":"5e6a46da33f53327e816708a"},"icon":"fas fa-users","title":"jobs.benefit1.title","description":"jobs.benefit1.description"},{"_id":{"$oid":"5e6a46da33f53327e816708b"},"icon":"far fa-eye","title":"jobs.benefit2.title","description":"jobs.benefit2.description"},{"_id":{"$oid":"5e6a46da33f53327e816708c"},"icon":"fas fa-trophy","title":"jobs.benefit3.title","description":"jobs.benefit3.description"},{"_id":{"$oid":"5e6a46da33f53327e816708d"},"icon":"far fa-handshake","title":"jobs.benefit4.title","description":"jobs.benefit4.description"},{"_id":{"$oid":"5e6a46da33f53327e816708e"},"icon":"far fa-clock","title":"jobs.benefit5.title","description":"jobs.benefit5.description"},{"_id":{"$oid":"5e6a46da33f53327e816708f"},"icon":"fas fa-terminal","title":"jobs.benefit6.title","description":"jobs.benefit6.description"}]